[
    {
        "word": "macchiato",
        "definition": [
            "a drink made with espresso coffee and a small amount of hot milk"
        ]
    },
    {
        "word": "exult",
        "definition": [
            "to feel and show that you are very excited and happy because of something that has happened"
        ]
    },
    {
        "word": "gigabyte",
        "definition": [
            "a unit of computer memory or data, equal to 109, or 1\u20090003, (= 1\u2009000\u2009000\u2009000) bytes",
            "a unit of computer memory or data, equal to 230, or 1\u20090243, (= 1\u2009073\u2009741\u2009824) bytes"
        ]
    },
    {
        "word": "terabyte",
        "definition": [
            "a unit of computer memory or data, equal to one million million, or 1012 (= 1\u2009000\u2009000\u2009000\u2009000) bytes",
            "a unit of computer memory or data, equal to 240 (= 1\u2009099\u2009511\u2009627\u2009776) bytes"
        ]
    },
    {
        "word": "undressed",
        "definition": [
            "not wearing any clothes"
        ]
    },
    {
        "word": "sensual",
        "definition": [
            "connected with your physical feelings; giving pleasure to your physical senses, especially sexual pleasure",
            "suggesting an interest in physical pleasure, especially sexual pleasure"
        ]
    },
    {
        "word": "inconsolable",
        "definition": [
            "very sad and unable to accept help or comfort"
        ]
    },
    {
        "word": "neurotic",
        "definition": [
            "caused by or having neurosis (= a mental illness in which a person has strong feelings of fear and worry)",
            "not behaving in a reasonable, calm way, because you are worried about something"
        ]
    },
    {
        "word": "humiliating",
        "definition": [
            "making somebody feel ashamed or stupid and lose the respect of other people"
        ]
    },
    {
        "word": "mortifying",
        "definition": [
            "making somebody feel very ashamed or embarrassed"
        ]
    },
    {
        "word": "theological",
        "definition": [
            "connected with the study of religion and beliefs"
        ]
    },
    {
        "word": "rematch",
        "definition": [
            "a match or game played again between the same people or teams, especially because neither side won the first match or game"
        ]
    },
    {
        "word": "ontological",
        "definition": [
            "connected with the branch of philosophy that deals with the nature of existence",
            "that shows the relationships between all the concepts and categories in a subject area"
        ]
    },
    {
        "word": "taxonomic",
        "definition": [
            "connected with the scientific process of classifying things (= arranging them into groups)"
        ]
    },
    {
        "word": "boulder",
        "definition": [
            "a very large rock which has been shaped by water or the weather"
        ]
    },
    {
        "word": "inviolable",
        "definition": [
            "that must be respected and not attacked or destroyed"
        ]
    },
    {
        "word": "resinous",
        "definition": [
            "producing, consisting of or smelling of resin "
        ]
    },
    {
        "word": "brittle",
        "definition": [
            "hard but easily broken",
            "a brittle mood or state of mind is one that appears to be happy or strong but is actually nervous and easily damaged",
            "hard and sharp in an unpleasant way"
        ]
    },
    {
        "word": "locker",
        "definition": [
            "a small cupboard that can be locked, where you can leave your clothes, bags, etc. while you play a sport or go somewhere"
        ]
    },
    {
        "word": "pow",
        "definition": [
            "used to express the sound of an explosion, a gun firing or somebody hitting somebody else"
        ]
    },
    {
        "word": "yesteryear",
        "definition": [
            "the past, especially a time when attitudes and ideas were different"
        ]
    },
    {
        "word": "overthrow",
        "definition": [
            "to remove a leader or a government from a position of power by force"
        ]
    },
    {
        "word": "incompatible",
        "definition": [
            "two actions, ideas, etc. that are incompatible are not acceptable or possible together because of basic differences",
            "two people who are incompatible are very different from each other and so are not able to live or work happily together",
            "two things that are incompatible are of different types so that they cannot be used or mixed together"
        ]
    },
    {
        "word": "dairyman",
        "definition": [
            "a man who works in a dairy",
            "a man who owns or manages a dairy and sells the products"
        ]
    },
    {
        "word": "chesty",
        "definition": [
            "suffering from or showing signs of chest disease"
        ]
    },
    {
        "word": "recurrent",
        "definition": [
            "that happens again and again"
        ]
    },
    {
        "word": "long-lasting",
        "definition": [
            "that can or does last for a long time"
        ]
    },
    {
        "word": "long-standing",
        "definition": [
            "that has existed or lasted for a long time"
        ]
    },
    {
        "word": "reap",
        "definition": [
            "to obtain something, especially something good, as a direct result of something that you have done",
            "to cut and collect a crop, especially wheat, from a field",
            "to benefit or suffer as a direct result of something that you have done",
            "you have to deal with the bad effects or results of something that you originally started"
        ]
    },
    {
        "word": "spark",
        "definition": [
            "to cause something to start or develop, especially suddenly",
            "to produce small flashes of fire or electricity"
        ]
    },
    {
        "word": "speckle",
        "definition": [
            "a small coloured mark or spot on a background of a different colour"
        ]
    }
]