[
    {
        "word": "maximal",
        "definition": [
            "as great or as large as possible"
        ]
    },
    {
        "word": "recidivism",
        "definition": [
            "the act or habit of continuing to commit crimes, and seeming unable to stop, even after being punished"
        ]
    },
    {
        "word": "recidivist",
        "definition": [
            "a person who continues to commit crimes, and seems unable to stop, even after being punished"
        ]
    },
    {
        "word": "cue",
        "definition": [
            "an action or event that is a signal for somebody to do something",
            "a few words or an action in a play that is a signal for another actor to do something",
            "a long wooden stick with a leather tip, used for hitting the ball in the games of billiards, pool and snooker",
            "at exactly the moment you expect or that is appropriate",
            "to copy what somebody else does as an example of how to behave or what to do"
        ]
    },
    {
        "word": "predictably",
        "definition": [
            "in such a way that you know in advance that something will happen or what it will be like",
            "in a way that you would expect and which is therefore boring"
        ]
    },
    {
        "word": "potentially",
        "definition": [
            "used to say that something may develop into something"
        ]
    },
    {
        "word": "initially",
        "definition": [
            "at the beginning"
        ]
    },
    {
        "word": "geographically",
        "definition": [
            "in a way that is connected with how the physical features of a place are arranged",
            "in a way that is connected with how a particular aspect of life or society is influenced by geography or varies according to geography"
        ]
    },
    {
        "word": "inimical",
        "definition": [
            "harmful to something; not helping something",
            "not friendly"
        ]
    },
    {
        "word": "unfriendly",
        "definition": [
            "not kind or pleasant to somebody"
        ]
    },
    {
        "word": "hostile",
        "definition": [
            "aggressive or unfriendly and ready to argue or fight",
            "strongly rejecting something",
            "making it difficult for something to happen or to be achieved",
            "belonging to a military enemy",
            "not wanted by the company that is to be bought"
        ]
    },
    {
        "word": "uncongenial",
        "definition": [
            "not friendly or pleasant to be with",
            "not pleasant; not making you feel relaxed; not suitable for your personality",
            "not suitable for something; not encouraging something"
        ]
    },
    {
        "word": "recrudescence",
        "definition": [
            "if there is recrudescence of something, especially something bad, it happens again"
        ]
    },
    {
        "word": "barrister",
        "definition": [
            "a lawyer in the UK who has the right to argue cases in the higher courts of law"
        ]
    },
    {
        "word": "fog-lamp",
        "definition": [
            "a very bright light on the front or back of a car to help the driver to see or be seen in fog"
        ]
    },
    {
        "word": "turtle",
        "definition": [
            "a large reptile with a hard round shell that lives in the sea",
            "any reptile with a large shell, for example a tortoise or terrapin",
            "to turn over completely while sailing"
        ]
    },
    {
        "word": "truism",
        "definition": [
            "a statement that is clearly true and does not therefore add anything interesting or important to a discussion"
        ]
    },
    {
        "word": "bromide",
        "definition": [
            "a chemical which contains bromine, used, especially in the past, to make people feel calm"
        ]
    },
    {
        "word": "stigma",
        "definition": [
            "negative feelings that people have about particular circumstances or characteristics that somebody may have",
            "the part in the middle of a flower where pollen is received"
        ]
    },
    {
        "word": "starvation",
        "definition": [
            "the state in which somebody suffers or dies because they have no food"
        ]
    },
    {
        "word": "proximal",
        "definition": [
            "located towards the centre of the body"
        ]
    },
    {
        "word": "promiscuity",
        "definition": [
            "behaviour that involves having many sexual partners"
        ]
    },
    {
        "word": "transpose",
        "definition": [
            "to change the order of two or more things",
            "to move or change something to a different place or environment or into a different form",
            "to write or play a piece of music or a series of notes in a different key"
        ]
    },
    {
        "word": "appendix",
        "definition": [
            "a small bag of tissue that is attached to the large intestine. In humans, the appendix has no clear function.",
            "a section giving extra information at the end of a book or document"
        ]
    },
    {
        "word": "subjunctive",
        "definition": [
            "in the form (or mood) that expresses wishes, possibility or uncertainty"
        ]
    },
    {
        "word": "short-term",
        "definition": [
            "lasting a short time; designed only for a short period of time in the future"
        ]
    },
    {
        "word": "shore",
        "definition": [
            "the land along the edge of the sea, the ocean or a lake",
            "an area that is by the sea or ocean, especially one where people go for a day or a holiday",
            "a country, especially one with a coast"
        ]
    },
    {
        "word": "bestial",
        "definition": [
            "cruel and horrible; of or like a beast"
        ]
    },
    {
        "word": "richness",
        "definition": [
            "the state of being rich in something, such as colour, minerals or interesting qualities"
        ]
    },
    {
        "word": "bifurcation",
        "definition": [
            "a place where a road, river, etc. divides into two different parts; the fact of this happening"
        ]
    },
    {
        "word": "predatory",
        "definition": [
            "living by killing and eating other animals",
            "using weaker people for their own financial or sexual advantage"
        ]
    },
    {
        "word": "exquisitely",
        "definition": [
            "in a way that is extremely beautiful or carefully made",
            "in a way that is very strongly felt",
            "in way that is very sensitive "
        ]
    }
]