[
    {
        "word": "rite",
        "definition": [
            "a ceremony performed by a particular group of people, often for religious purposes"
        ]
    },
    {
        "word": "imperial",
        "definition": [
            "connected with an empire",
            "connected with the system for measuring length, weight and volume using pounds, inches, etc."
        ]
    },
    {
        "word": "distinctly",
        "definition": [
            "in a way that is easily or clearly heard, seen, felt, etc.",
            "in a way that shows a quality that is easy to recognize",
            "definitely or extremely"
        ]
    },
    {
        "word": "chopsticks",
        "definition": [
            "a simple, cheerful piano tune for one or two players. Even people who have never properly learnt to play the piano often know how to play Chopsticks."
        ]
    },
    {
        "word": "japonica",
        "definition": [
            "a Japanese bush that is often grown in gardens, and that has red flowers and pale yellow fruit"
        ]
    },
    {
        "word": "sashimi",
        "definition": [
            "a Japanese dish consisting of slices of raw fish, served with sauce"
        ]
    },
    {
        "word": "grilling",
        "definition": [
            "a period of being questioned closely about your ideas, actions, etc."
        ]
    },
    {
        "word": "steaming",
        "definition": [
            "very angry",
            "very hot"
        ]
    },
    {
        "word": "cookbook",
        "definition": [
            "a book that gives instructions on cooking and how to cook individual dishes"
        ]
    },
    {
        "word": "daikon",
        "definition": [
            "a long white root vegetable that you can eat"
        ]
    },
    {
        "word": "teriyaki",
        "definition": [
            "a Japanese dish consisting of meat or fish that has been left in a sweet sauce and then cooked"
        ]
    },
    {
        "word": "turnip",
        "definition": [
            "a round white, or white and purple, root vegetable",
            "a large round yellow root vegetable"
        ]
    },
    {
        "word": "porcini",
        "definition": [
            "a type of wild mushroom, used in cooking"
        ]
    },
    {
        "word": "plum",
        "definition": [
            "a soft round fruit with smooth red or purple skin, that is sweet inside with a large flat seed",
            "a dark colour between red and purple"
        ]
    },
    {
        "word": "gage",
        "definition": [
            "an instrument for measuring the amount or level of something",
            "a measurement of how wide or thick something is",
            "a measurement of how wide the barrel of a gun is",
            "the distance between the rails of a railway track or the wheels of a train",
            "a fact or an event that can be used to estimate or judge something"
        ]
    },
    {
        "word": "redcurrant",
        "definition": [
            "a very small red berry that grows in bunches on a bush and can be eaten"
        ]
    },
    {
        "word": "veal",
        "definition": [
            "meat from a calf (= a young cow)"
        ]
    },
    {
        "word": "curry",
        "definition": [
            "a South Asian dish of meat, vegetables, etc. cooked in a hot spicy sauce, often served with rice"
        ]
    },
    {
        "word": "cityscape",
        "definition": [
            "the appearance of a city or urban area, especially in a picture; a picture of a city"
        ]
    },
    {
        "word": "contaminant",
        "definition": [
            "a substance that makes something impure"
        ]
    },
    {
        "word": "germane",
        "definition": [
            "connected with something in an important or appropriate way"
        ]
    },
    {
        "word": "vodka",
        "definition": [
            "a strong, clear alcoholic drink, made from grain, originally from Russia",
            "a glass of vodka"
        ]
    },
    {
        "word": "trigger-happy",
        "definition": [
            "too willing and quick to use violence, especially with guns"
        ]
    },
    {
        "word": "soporific",
        "definition": [
            "making you want to go to sleep"
        ]
    },
    {
        "word": "civility",
        "definition": [
            "polite behaviour",
            "remarks that are said only in order to be polite"
        ]
    },
    {
        "word": "knee-deep",
        "definition": [
            "up to your knees"
        ]
    },
    {
        "word": "knee-length",
        "definition": [
            "long enough to reach your knees"
        ]
    },
    {
        "word": "motherless",
        "definition": [
            "having no mother because she has died or does not live with you"
        ]
    },
    {
        "word": "fatherless",
        "definition": [
            "without a father, either because he has died or because he does not live with his children"
        ]
    },
    {
        "word": "childless",
        "definition": [
            "having no children"
        ]
    },
    {
        "word": "clanger",
        "definition": [
            "an obvious and embarrassing mistake"
        ]
    },
    {
        "word": "wart",
        "definition": [
            "a small hard spot that grows on your skin and that is caused by a virus",
            "a small hard spot like a wart on the bottom of the foot, which can be easily spread from person to person",
            "including all the bad or unpleasant features of somebody/something"
        ]
    },
    {
        "word": "urticaria",
        "definition": [
            "red spots on the skin that itch (= make you want to rub your skin with your nails), caused by an allergic reaction, for example to certain foods"
        ]
    },
    {
        "word": "clarity",
        "definition": [
            "the quality of being expressed clearly",
            "the ability to think about or understand something clearly",
            "if a picture, substance or sound has clarity, you can see or hear it very clearly, or see through it easily"
        ]
    },
    {
        "word": "psoriasis",
        "definition": [
            "a skin disease that causes rough red areas where the skin comes off in small pieces"
        ]
    },
    {
        "word": "so",
        "definition": [
            "to such a great degree",
            "very; extremely",
            "not to the same degree",
            "used to show the size, amount or number of something",
            "used to refer back to something that has already been mentioned",
            "also",
            "used to agree that something is true, especially when you are surprised",
            "used, often with a negative, before adjectives and noun phrases to emphasize something that you are saying",
            "used, especially by children, to say that what somebody says is not the case and the opposite is true",
            "used when you are showing somebody how to do something or telling them how something happened",
            "used at the end of a list to show that it continues in the same way",
            "used to give an important extra reason why something is true",
            "used after a number, an amount, etc. to show that it is not exact",
            "with the intention of doing something",
            "used to show that you accept something and will not try to change it or cannot change it",
            "used to show that you have finished talking about something",
            "used to suggest that something has not been successful or useful",
            "in such a way that"
        ]
    },
    {
        "word": "refine",
        "definition": [
            "to make a substance pure by taking other substances out of it",
            "to improve something by making small changes to it"
        ]
    },
    {
        "word": "basic",
        "definition": [
            "forming the part of something that is most necessary and from which other things develop",
            "of the simplest kind or at the simplest level",
            "necessary and important to all people",
            "before anything extra is added"
        ]
    },
    {
        "word": "upper",
        "definition": [
            "located above something else, especially something of the same type or the other of a pair",
            "at or near the top of something",
            "located away from the coast, on high ground or towards the north of an area",
            "to get an advantage over somebody so that you are in control of a particular situation",
            "to keep calm and hide your feelings when you are in pain or in a difficult situation"
        ]
    },
    {
        "word": "unusual",
        "definition": [
            "different from what is usual or normal",
            "different from other similar things and therefore interesting and attractive",
            "a category of very severe punishment that is banned under US law"
        ]
    },
    {
        "word": "surprising",
        "definition": [
            "causing surprise"
        ]
    },
    {
        "word": "surprisingly",
        "definition": [
            "in a way that causes surprise"
        ]
    }
]