[
    {
        "word": "dramatic",
        "definition": [
            "sudden, very great and often surprising",
            "exciting and impressive",
            "connected with the theatre or plays",
            "exaggerated in order to create a special effect and attract people\u2019s attention"
        ]
    },
    {
        "word": "victorious",
        "definition": [
            "having won a victory; that ends in victory"
        ]
    },
    {
        "word": "winning",
        "definition": [
            "that wins or has won something, for example a race or competition",
            "attractive in a way that makes other people like you",
            "a series of victories or successes"
        ]
    },
    {
        "word": "triumphant",
        "definition": [
            "very successful in a way that causes great pleasure",
            "showing great pleasure or joy about a victory or success"
        ]
    },
    {
        "word": "triumphal",
        "definition": [
            "done or made in order to celebrate a great success or victory"
        ]
    },
    {
        "word": "jubilant",
        "definition": [
            "feeling or showing great happiness because of a success"
        ]
    },
    {
        "word": "rejoicing",
        "definition": [
            "the happy celebration of something"
        ]
    },
    {
        "word": "gaydar",
        "definition": [
            "the supposed ability to recognize other people who are gay"
        ]
    },
    {
        "word": "pimply",
        "definition": [
            "having small raised red spots on the skin"
        ]
    },
    {
        "word": "philological",
        "definition": [
            "connected with the scientific study of the development of language or of a particular language"
        ]
    },
    {
        "word": "reckless",
        "definition": [
            "showing a lack of care about danger and the possible results of your actions"
        ]
    },
    {
        "word": "cystitis",
        "definition": [
            "an infection of the bladder, especially in women, that causes painful urination which happens often"
        ]
    },
    {
        "word": "urethritis",
        "definition": [
            "infection of the urethra"
        ]
    },
    {
        "word": "maggot",
        "definition": [
            "a creature like a small, short worm that is the young form of a fly and is found in meat and other food that is going bad. Maggots are often used as bait to catch fish."
        ]
    },
    {
        "word": "mastitis",
        "definition": [
            "painful swelling (= the condition of being larger or rounder than normal) of the breast or udder usually because of infection"
        ]
    },
    {
        "word": "knee-jerk",
        "definition": [
            "produced in reaction to something, without any serious thought"
        ]
    },
    {
        "word": "tenured",
        "definition": [
            "that you can keep permanently",
            "having the right to keep their job permanently"
        ]
    },
    {
        "word": "caliphate",
        "definition": [
            "the position of a caliph",
            "an area of land that is ruled over by a caliph"
        ]
    },
    {
        "word": "white-out",
        "definition": [
            "weather conditions in which there is so much snow or cloud that it is impossible to see anything"
        ]
    },
    {
        "word": "hijacker",
        "definition": [
            "a person who hijacks a plane or other vehicle"
        ]
    },
    {
        "word": "highwayman",
        "definition": [
            "a man, usually on a horse and carrying a gun, who stole from travellers on public roads in the past"
        ]
    },
    {
        "word": "factual",
        "definition": [
            "based on or containing facts"
        ]
    },
    {
        "word": "literal",
        "definition": [
            "being the most basic meaning of a word or phrase, rather than an extended or poetic meaning",
            "that follows the original words exactly",
            "not having or showing any imagination"
        ]
    },
    {
        "word": "strenuous",
        "definition": [
            "needing great effort and energy",
            "determined and showing great energy"
        ]
    },
    {
        "word": "sophistication",
        "definition": [
            "experience of the world and knowledge of fashion, culture and other things that people think are socially important",
            "the quality in a machine or system of being clever and complicated in the way that it works or is presented",
            "the ability to understand difficult or complicated ideas"
        ]
    },
    {
        "word": "edification",
        "definition": [
            "the improvement of somebody\u2019s mind or character"
        ]
    }
]